zeroproof/__init__.py
zeroproof/py.typed
zeroproof/autodiff/__init__.py
zeroproof/autodiff/graph.py
zeroproof/autodiff/policies.py
zeroproof/autodiff/projective.py
zeroproof/inference/__init__.py
zeroproof/inference/export.py
zeroproof/inference/mode.py
zeroproof/layers/__init__.py
zeroproof/layers/fru.py
zeroproof/layers/normalization.py
zeroproof/layers/projective_rational.py
zeroproof/layers/scm_rational.py
zeroproof/losses/__init__.py
zeroproof/losses/coverage.py
zeroproof/losses/implicit.py
zeroproof/losses/margin.py
zeroproof/losses/sign.py
zeroproof/metrics/__init__.py
zeroproof/metrics/pole_2d.py
zeroproof/scm/__init__.py
zeroproof/scm/fracterm.py
zeroproof/scm/ops.py
zeroproof/scm/sign.py
zeroproof/scm/value.py
zeroproof/training/__init__.py
zeroproof/training/gap.py
zeroproof/training/sampler.py
zeroproof/training/targets.py
zeroproof/training/trainer.py
zeroproof/utils/__init__.py
zeroproof/utils/ieee_bridge.py
zeroproofml/__init__.py
zeroproofml/benchmark.py
zeroproofml/binary_metrics.py
zeroproofml/experiment_protocol.py
zeroproofml/resources.py
zeroproofml-0.4.1.dist-info/licenses/LICENSE
zeroproofml-0.4.1.dist-info/METADATA
zeroproofml-0.4.1.dist-info/WHEEL
zeroproofml-0.4.1.dist-info/top_level.txt
zeroproofml-0.4.1.dist-info/RECORD
