Metadata-Version: 2.4
Name: zeroproofml
Version: 0.4.1
Summary: Signed Common Meadow arithmetic for stable machine learning
Author-email: ZeroProof Team <zeroproof@example.com>
License-Expression: MIT
Project-URL: Homepage, https://zeroproofml.com
Project-URL: Repository, https://github.com/domezsolt/zeroproofml
Project-URL: Documentation, https://github.com/domezsolt/zeroproofml/tree/main/docs
Project-URL: Issues, https://github.com/domezsolt/zeroproofml/issues
Keywords: signed-common-meadow,scm,machine-learning,numerical-stability,autodiff,robustness
Classifier: Development Status :: 3 - Alpha
Classifier: Intended Audience :: Science/Research
Classifier: Programming Language :: Python
Classifier: Programming Language :: Python :: 3
Classifier: Programming Language :: Python :: 3 :: Only
Classifier: Programming Language :: Python :: 3.10
Classifier: Programming Language :: Python :: 3.11
Classifier: Programming Language :: Python :: 3.12
Classifier: Programming Language :: Python :: 3.13
Classifier: Topic :: Scientific/Engineering :: Artificial Intelligence
Requires-Python: >=3.10
License-File: LICENSE
Provides-Extra: torch
Requires-Dist: torch>=1.12; (platform_system != "Darwin" or platform_machine != "arm64") and extra == "torch"
Provides-Extra: jax
Requires-Dist: jax>=0.4.14; extra == "jax"
Requires-Dist: jaxlib>=0.4.14; (platform_machine != "arm64" or platform_system != "Darwin") and extra == "jax"
Provides-Extra: dev
Requires-Dist: numpy>=1.23; extra == "dev"
Requires-Dist: pytest>=7.4; extra == "dev"
Requires-Dist: pytest-cov>=4.1; extra == "dev"
Requires-Dist: hypothesis>=6.88; extra == "dev"
Requires-Dist: black>=23.7; extra == "dev"
Requires-Dist: ruff>=0.4.0; extra == "dev"
Requires-Dist: isort>=5.12; extra == "dev"
Requires-Dist: mypy>=1.4; extra == "dev"
Requires-Dist: pre-commit>=3.3; extra == "dev"
Provides-Extra: all
Requires-Dist: torch>=1.12; (platform_system != "Darwin" or platform_machine != "arm64") and extra == "all"
Requires-Dist: jax>=0.4.14; extra == "all"
Requires-Dist: jaxlib>=0.4.14; (platform_machine != "arm64" or platform_system != "Darwin") and extra == "all"
Dynamic: license-file
